langutils_anuragjha/__init__.py
langutils_anuragjha/openai_utils.py
langutils_anuragjha-0.1.0.dist-info/LICENSE
langutils_anuragjha-0.1.0.dist-info/METADATA
langutils_anuragjha-0.1.0.dist-info/WHEEL
langutils_anuragjha-0.1.0.dist-info/RECORD
