Metadata-Version: 2.1
Name: langutils_anuragjha
Version: 0.1.0
Summary: Utils for large language model
Author: Anurag Jha
Author-email: toanuragjha@gmail.com
Requires-Python: >=3.10,<4.0
Classifier: Programming Language :: Python :: 3
Classifier: Programming Language :: Python :: 3.10
Classifier: Programming Language :: Python :: 3.11
Classifier: Programming Language :: Python :: 3.12
Requires-Dist: pytest (==7.4.4)
Requires-Dist: pytest-asyncio (==0.23.3)
